intake_esm/__init__.py
intake_esm/_search.py
intake_esm/_version.py
intake_esm/cat.py
intake_esm/core.py
intake_esm/derived.py
intake_esm/py.typed
intake_esm/source.py
intake_esm/tutorial.py
intake_esm/utils.py
intake_esm_access-2025.10.14.dist-info/licenses/LICENSE
intake_esm_access-2025.10.14.dist-info/METADATA
intake_esm_access-2025.10.14.dist-info/WHEEL
intake_esm_access-2025.10.14.dist-info/entry_points.txt
intake_esm_access-2025.10.14.dist-info/top_level.txt
intake_esm_access-2025.10.14.dist-info/RECORD
