Metadata-Version: 2.4
Name: intake-esm-access
Version: 2025.10.14
Summary: An intake plugin for parsing an Earth System Model (ESM) catalog and loading netCDF files and/or Zarr stores into Xarray datasets. This is the ACCESS-NRI bleeding edge fork.
Maintainer-email: ACCESS-NRI <charles.turner@anu.edu.au>
License: Apache Software License 2.0
Project-URL: Documentation, https://intake-esm.readthedocs.io
Project-URL: Homepage, https://intake-esm.readthedocs.io
Project-URL: Source, https://github.com/access-nri/intake-esm
Project-URL: Tracker, https://github.com/access-nri/intake-esm/issues
Keywords: catalog,intake,xarray
Classifier: Development Status :: 4 - Beta
Classifier: Intended Audience :: Science/Research
Classifier: License :: OSI Approved :: Apache Software License
Classifier: Operating System :: OS Independent
Classifier: Programming Language :: Python :: 3
Classifier: Programming Language :: Python :: 3.10
Classifier: Programming Language :: Python :: 3.11
Classifier: Programming Language :: Python :: 3.12
Classifier: Programming Language :: Python :: 3.13
Classifier: Programming Language :: Python
Classifier: Topic :: Scientific/Engineering
Requires-Python: >=3.10
License-File: LICENSE
Requires-Dist: dask[complete]>=2024.12
Requires-Dist: fastprogress>=1.0.0
Requires-Dist: fsspec>=2024.12
Requires-Dist: intake>=2.0.0
Requires-Dist: itables
Requires-Dist: netCDF4>=1.5.5
Requires-Dist: pandas>=2.1.0
Requires-Dist: polars>=1.24.0
Requires-Dist: pydantic>=2.0
Requires-Dist: pydap!=3.5.5
Requires-Dist: requests>=2.24.0
Requires-Dist: xarray>=2024.10
Requires-Dist: zarr!=3.0.*,>=2.12
Dynamic: license-file
